{
  "appveyor": {
    "rates": {
      "2021-02-28T09:05:00-05:00": 0,
      "2021-02-28T09:10:00-05:00": 0,
      "2021-02-28T09:15:00-05:00": 0,
      "2021-02-28T09:20:00-05:00": 0,
      "2021-02-28T09:25:00-05:00": 0,
      "2021-02-28T09:30:00-05:00": 0,
      "2021-02-28T09:35:00-05:00": 0,
      "2021-02-28T09:40:00-05:00": 0,
      "2021-02-28T09:45:00-05:00": 0,
      "2021-02-28T09:50:00-05:00": 0,
      "2021-02-28T09:55:00-05:00": 0,
      "2021-02-28T10:00:00-05:00": 0,
      "2021-02-28T10:05:00-05:00": 0,
      "2021-02-28T10:10:00-05:00": 0,
      "2021-02-28T10:15:00-05:00": 0,
      "2021-02-28T10:20:00-05:00": 0,
      "2021-02-28T10:25:00-05:00": 0,
      "2021-02-28T10:30:00-05:00": 0,
      "2021-02-28T10:35:00-05:00": 0,
      "2021-02-28T10:40:00-05:00": 0,
      "2021-02-28T10:45:00-05:00": 0,
      "2021-02-28T10:50:00-05:00": 0,
      "2021-02-28T10:55:00-05:00": 0,
      "2021-02-28T11:00:00-05:00": 0,
      "2021-02-28T11:05:00-05:00": 0,
      "2021-02-28T11:10:00-05:00": 0,
      "2021-02-28T11:15:00-05:00": 0,
      "2021-02-28T11:20:00-05:00": 0,
      "2021-02-28T11:25:00-05:00": 0,
      "2021-02-28T11:30:00-05:00": 0,
      "2021-02-28T11:35:00-05:00": 0,
      "2021-02-28T11:40:00-05:00": 0,
      "2021-02-28T11:45:00-05:00": 0,
      "2021-02-28T11:50:00-05:00": 0,
      "2021-02-28T11:55:00-05:00": 0,
      "2021-02-28T12:00:00-05:00": 0,
      "2021-02-28T12:05:00-05:00": 0,
      "2021-02-28T12:10:00-05:00": 0,
      "2021-02-28T12:15:00-05:00": 0,
      "2021-02-28T12:20:00-05:00": 0,
      "2021-02-28T12:25:00-05:00": 0,
      "2021-02-28T12:30:00-05:00": 0,
      "2021-02-28T12:35:00-05:00": 0,
      "2021-02-28T12:40:00-05:00": 0,
      "2021-02-28T12:45:00-05:00": 0,
      "2021-02-28T12:50:00-05:00": 0,
      "2021-02-28T12:55:00-05:00": 0,
      "2021-02-28T13:00:00-05:00": 0,
      "2021-02-28T13:05:00-05:00": 0,
      "2021-02-28T13:10:00-05:00": 0,
      "2021-02-28T13:15:00-05:00": 0,
      "2021-02-28T13:20:00-05:00": 1,
      "2021-02-28T13:25:00-05:00": 0,
      "2021-02-28T13:30:00-05:00": 0,
      "2021-02-28T13:35:00-05:00": 0,
      "2021-02-28T13:40:00-05:00": 0,
      "2021-02-28T13:45:00-05:00": 0,
      "2021-02-28T13:50:00-05:00": 0,
      "2021-02-28T13:55:00-05:00": 0,
      "2021-02-28T14:00:00-05:00": 0,
      "2021-02-28T14:05:00-05:00": 0,
      "2021-02-28T14:10:00-05:00": 0,
      "2021-02-28T14:15:00-05:00": 0,
      "2021-02-28T14:20:00-05:00": 0,
      "2021-02-28T14:25:00-05:00": 0,
      "2021-02-28T14:30:00-05:00": 0,
      "2021-02-28T14:35:00-05:00": 0,
      "2021-02-28T14:40:00-05:00": 0,
      "2021-02-28T14:45:00-05:00": 0,
      "2021-02-28T14:50:00-05:00": 0,
      "2021-02-28T14:55:00-05:00": 0,
      "2021-02-28T15:00:00-05:00": 0,
      "2021-02-28T15:05:00-05:00": 0,
      "2021-02-28T15:10:00-05:00": 0,
      "2021-02-28T15:15:00-05:00": 0,
      "2021-02-28T15:20:00-05:00": 0,
      "2021-02-28T15:25:00-05:00": 0,
      "2021-02-28T15:30:00-05:00": 0,
      "2021-02-28T15:35:00-05:00": 0,
      "2021-02-28T15:40:00-05:00": 0,
      "2021-02-28T15:45:00-05:00": 0,
      "2021-02-28T15:50:00-05:00": 0,
      "2021-02-28T15:55:00-05:00": 0,
      "2021-02-28T16:00:00-05:00": 0,
      "2021-02-28T16:05:00-05:00": 0,
      "2021-02-28T16:10:00-05:00": 0,
      "2021-02-28T16:15:00-05:00": 0,
      "2021-02-28T16:20:00-05:00": 0,
      "2021-02-28T16:25:00-05:00": 0,
      "2021-02-28T16:30:00-05:00": 0,
      "2021-02-28T16:35:00-05:00": 0,
      "2021-02-28T16:40:00-05:00": 0,
      "2021-02-28T16:45:00-05:00": 0,
      "2021-02-28T16:50:00-05:00": 0,
      "2021-02-28T16:55:00-05:00": 0,
      "2021-02-28T17:00:00-05:00": 0
    },
    "repos": {
      "conda-forge/clblast-feedstock": 1,
      "conda-forge/qgis-feedstock": 1,
      "conda-forge/qt-feedstock": 7,
      "conda-forge/qt5reactor-feedstock": 2,
      "conda-forge/qtwebkit-feedstock": 1,
      "conda-forge/r-arrow-feedstock": 5,
      "conda-forge/r-asbio-feedstock": 1,
      "conda-forge/r-backports-feedstock": 1,
      "conda-forge/r-base-feedstock": 1,
      "conda-forge/r-betareg-feedstock": 1,
      "conda-forge/r-gghighlight-feedstock": 1,
      "conda-forge/r-mass-feedstock": 1,
      "conda-forge/r-openmx-feedstock": 30,
      "conda-forge/r-pbkrtest-feedstock": 1,
      "conda-forge/r-plsvarsel-feedstock": 1,
      "conda-forge/r-pracma-feedstock": 1,
      "conda-forge/r-princurve-feedstock": 1,
      "conda-forge/r-raster-feedstock": 1,
      "conda-forge/r-rcppziggurat-feedstock": 1,
      "conda-forge/r-rgl-feedstock": 1,
      "conda-forge/r-spatest-feedstock": 1,
      "conda-forge/r-spatstat.data-feedstock": 1,
      "conda-forge/radical.analytics-feedstock": 1,
      "conda-forge/rapidsim-feedstock": 1,
      "conda-forge/rbdl-feedstock": 11,
      "conda-forge/rdkit-feedstock": 1,
      "conda-forge/requests-feedstock": 1,
      "conda-forge/responder-feedstock": 1,
      "conda-forge/root-feedstock": 5,
      "conda-forge/roslibpy-feedstock": 1,
      "conda-forge/ruamel.yaml-feedstock": 3,
      "conda-forge/ruby-feedstock": 1,
      "conda-forge/s3transfer-feedstock": 1,
      "conda-forge/salib-feedstock": 1,
      "conda-forge/saws-feedstock": 2,
      "conda-forge/scikit-bio-feedstock": 1,
      "conda-forge/scikit-learn-feedstock": 2,
      "conda-forge/scikit-surprise-feedstock": 2,
      "conda-forge/scilab-feedstock": 1,
      "conda-forge/scipy-feedstock": 3,
      "conda-forge/scrypt-feedstock": 1,
      "conda-forge/sdl2_image-feedstock": 2,
      "conda-forge/sdl2_mixer-feedstock": 2,
      "conda-forge/seabreeze-feedstock": 4,
      "conda-forge/seekpath-feedstock": 1,
      "conda-forge/shapely-feedstock": 1,
      "conda-forge/shogun-feedstock": 2,
      "conda-forge/simbody-feedstock": 5,
      "conda-forge/simhash-feedstock": 1,
      "conda-forge/simpleitk-feedstock": 3,
      "conda-forge/singular-feedstock": 1,
      "conda-forge/sip-feedstock": 1,
      "conda-forge/sisl-feedstock": 1,
      "conda-forge/sos-notebook-feedstock": 1,
      "conda-forge/spacy-feedstock": 1,
      "conda-forge/sparsehash-c11-feedstock": 2,
      "conda-forge/spdlib-feedstock": 1,
      "conda-forge/speclite-feedstock": 2,
      "conda-forge/sphinxcontrib-bibtex-feedstock": 1,
      "conda-forge/spinsfast-feedstock": 1,
      "conda-forge/spyder-kernels-feedstock": 1,
      "conda-forge/sqlalchemy-utils-feedstock": 1,
      "conda-forge/sqlite-feedstock": 1,
      "conda-forge/squashfs-tools-feedstock": 1,
      "conda-forge/srsly-feedstock": 1,
      "conda-forge/staged-recipes": 3276,
      "conda-forge/starlette-feedstock": 3,
      "conda-forge/stevedore-feedstock": 1,
      "conda-forge/suitesparse-feedstock": 2,
      "conda-forge/swiglpk-feedstock": 1,
      "conda-forge/tapi-feedstock": 1,
      "conda-forge/tar-feedstock": 1,
      "conda-forge/tbb-feedstock": 1,
      "conda-forge/tempest-remap-feedstock": 2,
      "conda-forge/tensorboard-feedstock": 1,
      "conda-forge/tensorflow-feedstock": 3,
      "conda-forge/terraform-provider-alicloud-feedstock": 1,
      "conda-forge/terraform-provider-aws-feedstock": 1,
      "conda-forge/terraform-provider-cloudstack-feedstock": 2,
      "conda-forge/terraform-provider-cobbler-feedstock": 6,
      "conda-forge/terraform-provider-logicmonitor-feedstock": 1,
      "conda-forge/terraform-provider-pagerduty-feedstock": 1,
      "conda-forge/terrainbento-feedstock": 1,
      "conda-forge/texlive-core-feedstock": 1,
      "conda-forge/textacy-feedstock": 1,
      "conda-forge/textdistance-feedstock": 1,
      "conda-forge/theanolm-feedstock": 2,
      "conda-forge/thermotools-feedstock": 1,
      "conda-forge/thrift-cpp-feedstock": 1,
      "conda-forge/tiledb-feedstock": 1,
      "conda-forge/tk-feedstock": 1,
      "conda-forge/tmux-feedstock": 1,
      "conda-forge/tomopy-feedstock": 2,
      "conda-forge/topologytoolkit-feedstock": 1,
      "conda-forge/trimesh-feedstock": 2,
      "conda-forge/trio-asyncio-feedstock": 13,
      "conda-forge/tweepy-feedstock": 1,
      "conda-forge/typed-ast-feedstock": 1,
      "conda-forge/typing_extensions-feedstock": 1,
      "conda-forge/u3d-feedstock": 3,
      "conda-forge/ucx-split-feedstock": 1,
      "conda-forge/udunits2-feedstock": 1,
      "conda-forge/urdfdom-feedstock": 1,
      "conda-forge/vc-feedstock": 1,
      "conda-forge/vigra-feedstock": 1,
      "conda-forge/vmd-python-feedstock": 1,
      "conda-forge/vmprof-feedstock": 1,
      "conda-forge/vtk-feedstock": 2,
      "conda-forge/wabt-feedstock": 1,
      "conda-forge/watchdog-feedstock": 1,
      "conda-forge/watchtower-feedstock": 2,
      "conda-forge/westpa-feedstock": 2,
      "conda-forge/wfdb-feedstock": 1,
      "conda-forge/wradlib-feedstock": 1,
      "conda-forge/wstools-feedstock": 1,
      "conda-forge/xeus-feedstock": 1,
      "conda-forge/xeus-python-feedstock": 1,
      "conda-forge/xorg-damageproto-feedstock": 1,
      "conda-forge/xorg-xf86vidmodeproto-feedstock": 1,
      "conda-forge/xrootd-feedstock": 1,
      "conda-forge/xskillscore-feedstock": 1,
      "conda-forge/xtensor-r-feedstock": 1,
      "conda-forge/xz-feedstock": 4,
      "conda-forge/yaafe-feedstock": 1,
      "conda-forge/yaml-cpp-feedstock": 2,
      "conda-forge/z5py-feedstock": 10,
      "conda-forge/zetcd-feedstock": 3,
      "conda-forge/zziplib-feedstock": 5
    },
    "total": 1
  },
  "azure-pipelines": {
    "rates": {
      "2021-02-28T09:05:00-05:00": 3,
      "2021-02-28T09:10:00-05:00": 0,
      "2021-02-28T09:15:00-05:00": 0,
      "2021-02-28T09:20:00-05:00": 0,
      "2021-02-28T09:25:00-05:00": 0,
      "2021-02-28T09:30:00-05:00": 2,
      "2021-02-28T09:35:00-05:00": 2,
      "2021-02-28T09:40:00-05:00": 4,
      "2021-02-28T09:45:00-05:00": 3,
      "2021-02-28T09:50:00-05:00": 2,
      "2021-02-28T09:55:00-05:00": 38,
      "2021-02-28T10:00:00-05:00": 21,
      "2021-02-28T10:05:00-05:00": 11,
      "2021-02-28T10:10:00-05:00": 11,
      "2021-02-28T10:15:00-05:00": 3,
      "2021-02-28T10:20:00-05:00": 6,
      "2021-02-28T10:25:00-05:00": 4,
      "2021-02-28T10:30:00-05:00": 1,
      "2021-02-28T10:35:00-05:00": 14,
      "2021-02-28T10:40:00-05:00": 3,
      "2021-02-28T10:45:00-05:00": 3,
      "2021-02-28T10:50:00-05:00": 5,
      "2021-02-28T10:55:00-05:00": 4,
      "2021-02-28T11:00:00-05:00": 2,
      "2021-02-28T11:05:00-05:00": 0,
      "2021-02-28T11:10:00-05:00": 3,
      "2021-02-28T11:15:00-05:00": 4,
      "2021-02-28T11:20:00-05:00": 3,
      "2021-02-28T11:25:00-05:00": 7,
      "2021-02-28T11:30:00-05:00": 6,
      "2021-02-28T11:35:00-05:00": 11,
      "2021-02-28T11:40:00-05:00": 9,
      "2021-02-28T11:45:00-05:00": 7,
      "2021-02-28T11:50:00-05:00": 13,
      "2021-02-28T11:55:00-05:00": 8,
      "2021-02-28T12:00:00-05:00": 2,
      "2021-02-28T12:05:00-05:00": 6,
      "2021-02-28T12:10:00-05:00": 2,
      "2021-02-28T12:15:00-05:00": 3,
      "2021-02-28T12:20:00-05:00": 3,
      "2021-02-28T12:25:00-05:00": 3,
      "2021-02-28T12:30:00-05:00": 2,
      "2021-02-28T12:35:00-05:00": 3,
      "2021-02-28T12:40:00-05:00": 4,
      "2021-02-28T12:45:00-05:00": 0,
      "2021-02-28T12:50:00-05:00": 8,
      "2021-02-28T12:55:00-05:00": 15,
      "2021-02-28T13:00:00-05:00": 12,
      "2021-02-28T13:05:00-05:00": 18,
      "2021-02-28T13:10:00-05:00": 11,
      "2021-02-28T13:15:00-05:00": 15,
      "2021-02-28T13:20:00-05:00": 9,
      "2021-02-28T13:25:00-05:00": 4,
      "2021-02-28T13:30:00-05:00": 4,
      "2021-02-28T13:35:00-05:00": 1,
      "2021-02-28T13:40:00-05:00": 11,
      "2021-02-28T13:45:00-05:00": 2,
      "2021-02-28T13:50:00-05:00": 4,
      "2021-02-28T13:55:00-05:00": 1,
      "2021-02-28T14:00:00-05:00": 18,
      "2021-02-28T14:05:00-05:00": 13,
      "2021-02-28T14:10:00-05:00": 9,
      "2021-02-28T14:15:00-05:00": 1,
      "2021-02-28T14:20:00-05:00": 4,
      "2021-02-28T14:25:00-05:00": 9,
      "2021-02-28T14:30:00-05:00": 8,
      "2021-02-28T14:35:00-05:00": 2,
      "2021-02-28T14:40:00-05:00": 4,
      "2021-02-28T14:45:00-05:00": 1,
      "2021-02-28T14:50:00-05:00": 7,
      "2021-02-28T14:55:00-05:00": 1,
      "2021-02-28T15:00:00-05:00": 1,
      "2021-02-28T15:05:00-05:00": 3,
      "2021-02-28T15:10:00-05:00": 1,
      "2021-02-28T15:15:00-05:00": 1,
      "2021-02-28T15:20:00-05:00": 5,
      "2021-02-28T15:25:00-05:00": 1,
      "2021-02-28T15:30:00-05:00": 2,
      "2021-02-28T15:35:00-05:00": 60,
      "2021-02-28T15:40:00-05:00": 13,
      "2021-02-28T15:45:00-05:00": 11,
      "2021-02-28T15:50:00-05:00": 7,
      "2021-02-28T15:55:00-05:00": 4,
      "2021-02-28T16:00:00-05:00": 2,
      "2021-02-28T16:05:00-05:00": 3,
      "2021-02-28T16:10:00-05:00": 3,
      "2021-02-28T16:15:00-05:00": 1,
      "2021-02-28T16:20:00-05:00": 7,
      "2021-02-28T16:25:00-05:00": 4,
      "2021-02-28T16:30:00-05:00": 8,
      "2021-02-28T16:35:00-05:00": 26,
      "2021-02-28T16:40:00-05:00": 18,
      "2021-02-28T16:45:00-05:00": 11,
      "2021-02-28T16:50:00-05:00": 5,
      "2021-02-28T16:55:00-05:00": 1,
      "2021-02-28T17:00:00-05:00": 2
    },
    "repos": {
      "conda-forge/ambiance-feedstock": 2,
      "conda-forge/bitarray-feedstock": 39,
      "conda-forge/broot-feedstock": 5,
      "conda-forge/cadquery-feedstock": 2,
      "conda-forge/clang-compiler-activation-feedstock": 32,
      "conda-forge/conda-forge-repodata-patches-feedstock": 2,
      "conda-forge/dftbplus-feedstock": 7,
      "conda-forge/dlfcn-win32-feedstock": 4,
      "conda-forge/dlpoly-py-feedstock": 4,
      "conda-forge/dmba-feedstock": 2,
      "conda-forge/faiss-split-feedstock": 20,
      "conda-forge/find-kedro-feedstock": 2,
      "conda-forge/freecad-feedstock": 14,
      "conda-forge/frictionqpotfem-feedstock": 8,
      "conda-forge/gammapy-feedstock": 15,
      "conda-forge/gazebo-feedstock": 3,
      "conda-forge/gitpython-feedstock": 4,
      "conda-forge/google-api-core-feedstock": 5,
      "conda-forge/googleapis-common-protos-feedstock": 69,
      "conda-forge/goosefem-feedstock": 11,
      "conda-forge/httpx-feedstock": 2,
      "conda-forge/imagemagick-feedstock": 6,
      "conda-forge/isa-l-feedstock": 4,
      "conda-forge/jupyter_conda-feedstock": 2,
      "conda-forge/kim_property-feedstock": 4,
      "conda-forge/libmatio-feedstock": 11,
      "conda-forge/libsemigroups-feedstock": 8,
      "conda-forge/ligo.skymap-feedstock": 8,
      "conda-forge/llvmdev-feedstock": 7,
      "conda-forge/lyx-feedstock": 22,
      "conda-forge/mdanalysis-feedstock": 21,
      "conda-forge/mdanalysistests-feedstock": 46,
      "conda-forge/metaio-feedstock": 5,
      "conda-forge/mkdocstrings-feedstock": 2,
      "conda-forge/nbsphinx-feedstock": 2,
      "conda-forge/p4p-feedstock": 13,
      "conda-forge/pdal-feedstock": 4,
      "conda-forge/pdfplumber-feedstock": 2,
      "conda-forge/pngquant-feedstock": 3,
      "conda-forge/portion-feedstock": 4,
      "conda-forge/postgis-feedstock": 6,
      "conda-forge/pyathena-feedstock": 4,
      "conda-forge/pyglotaran-feedstock": 6,
      "conda-forge/pymeeus-feedstock": 2,
      "conda-forge/pynamodb-feedstock": 2,
      "conda-forge/pynio-feedstock": 7,
      "conda-forge/pyqt-feedstock": 39,
      "conda-forge/python3-saml-feedstock": 2,
      "conda-forge/pytkdocs-feedstock": 4,
      "conda-forge/qwt-feedstock": 7,
      "conda-forge/r-farver-feedstock": 18,
      "conda-forge/r-hmisc-feedstock": 18,
      "conda-forge/r-tibble-feedstock": 27,
      "conda-forge/r-tune-feedstock": 12,
      "conda-forge/r-turfr-feedstock": 3,
      "conda-forge/r-weights-feedstock": 7,
      "conda-forge/r-xtensor-feedstock": 35,
      "conda-forge/rdata-feedstock": 4,
      "conda-forge/reacnetgenerator-feedstock": 13,
      "conda-forge/readchar-feedstock": 4,
      "conda-forge/remi-feedstock": 2,
      "conda-forge/rich-feedstock": 72,
      "conda-forge/robotframework-seleniumlibrary-feedstock": 8,
      "conda-forge/root-feedstock": 2,
      "conda-forge/runner-feedstock": 14,
      "conda-forge/rust-feedstock": 5,
      "conda-forge/s2geometry-feedstock": 4,
      "conda-forge/sagemaker-python-sdk-feedstock": 13,
      "conda-forge/scikit-mobility-feedstock": 2,
      "conda-forge/shogun-cpp-feedstock": 5,
      "conda-forge/singledispatch-feedstock": 2,
      "conda-forge/singularity-compose-feedstock": 5,
      "conda-forge/sip-feedstock": 68,
      "conda-forge/sklearn-pandas-feedstock": 11,
      "conda-forge/soci-feedstock": 11,
      "conda-forge/spacy-model-en_core_web-feedstock": 4,
      "conda-forge/spampy-feedstock": 2,
      "conda-forge/sphinx-book-theme-feedstock": 6,
      "conda-forge/sphinx-multitoc-numbering-feedstock": 2,
      "conda-forge/sphinx-notfound-page-feedstock": 4,
      "conda-forge/sphinxcontrib-details-directive-feedstock": 2,
      "conda-forge/sphinxcontrib-restbuilder-feedstock": 2,
      "conda-forge/spotipy-feedstock": 16,
      "conda-forge/srtm.py-feedstock": 2,
      "conda-forge/staged-recipes": 288,
      "conda-forge/stress-ng-feedstock": 2,
      "conda-forge/structdbrest-feedstock": 9,
      "conda-forge/sunpy-feedstock": 20,
      "conda-forge/supervisor-feedstock": 11,
      "conda-forge/sweetviz-feedstock": 2,
      "conda-forge/tempest-remap-feedstock": 5,
      "conda-forge/thorlabs-apt-protocol-feedstock": 4,
      "conda-forge/tifffile-feedstock": 4,
      "conda-forge/tike-feedstock": 2,
      "conda-forge/tilt-feedstock": 8,
      "conda-forge/topologytoolkit-feedstock": 25,
      "conda-forge/torchsde-feedstock": 61,
      "conda-forge/tributary-feedstock": 18,
      "conda-forge/trimesh-feedstock": 2,
      "conda-forge/ttyd-feedstock": 4,
      "conda-forge/twisted-feedstock": 29,
      "conda-forge/typhos-feedstock": 4,
      "conda-forge/umarkdown-feedstock": 12,
      "conda-forge/universal-ctags-feedstock": 6,
      "conda-forge/verta-feedstock": 11,
      "conda-forge/vim-feedstock": 130,
      "conda-forge/vscode-icons-feedstock": 24,
      "conda-forge/vyper-feedstock": 4,
      "conda-forge/wquantiles-feedstock": 2,
      "conda-forge/xeus-cling-feedstock": 12,
      "conda-forge/xeus-feedstock": 10,
      "conda-forge/xgboost-feedstock": 4,
      "conda-forge/xmlsec-feedstock": 48,
      "conda-forge/xproperty-feedstock": 8,
      "conda-forge/xsimd-feedstock": 10,
      "conda-forge/xtb-python-feedstock": 15,
      "conda-forge/xtensor-blas-feedstock": 8,
      "conda-forge/xtensor-feedstock": 10,
      "conda-forge/xtensor-io-feedstock": 16,
      "conda-forge/xtensor-julia-feedstock": 6,
      "conda-forge/xtensor-python-feedstock": 57,
      "conda-forge/xtensor-r-feedstock": 18,
      "conda-forge/xtl-feedstock": 10,
      "conda-forge/yaqd-thorlabs-feedstock": 4,
      "conda-forge/yaqd-vici-feedstock": 2,
      "conda-forge/yaspin-feedstock": 2,
      "conda-forge/zmqpp-feedstock": 6,
      "conda-forge/zstandard-feedstock": 19
    },
    "total": 633
  },
  "circleci": {
    "rates": {
      "2021-02-28T09:05:00-05:00": 0,
      "2021-02-28T09:10:00-05:00": 0,
      "2021-02-28T09:15:00-05:00": 0,
      "2021-02-28T09:20:00-05:00": 0,
      "2021-02-28T09:25:00-05:00": 0,
      "2021-02-28T09:30:00-05:00": 0,
      "2021-02-28T09:35:00-05:00": 0,
      "2021-02-28T09:40:00-05:00": 0,
      "2021-02-28T09:45:00-05:00": 0,
      "2021-02-28T09:50:00-05:00": 1,
      "2021-02-28T09:55:00-05:00": 0,
      "2021-02-28T10:00:00-05:00": 0,
      "2021-02-28T10:05:00-05:00": 0,
      "2021-02-28T10:10:00-05:00": 0,
      "2021-02-28T10:15:00-05:00": 0,
      "2021-02-28T10:20:00-05:00": 1,
      "2021-02-28T10:25:00-05:00": 0,
      "2021-02-28T10:30:00-05:00": 0,
      "2021-02-28T10:35:00-05:00": 0,
      "2021-02-28T10:40:00-05:00": 0,
      "2021-02-28T10:45:00-05:00": 0,
      "2021-02-28T10:50:00-05:00": 0,
      "2021-02-28T10:55:00-05:00": 0,
      "2021-02-28T11:00:00-05:00": 0,
      "2021-02-28T11:05:00-05:00": 0,
      "2021-02-28T11:10:00-05:00": 0,
      "2021-02-28T11:15:00-05:00": 0,
      "2021-02-28T11:20:00-05:00": 0,
      "2021-02-28T11:25:00-05:00": 0,
      "2021-02-28T11:30:00-05:00": 0,
      "2021-02-28T11:35:00-05:00": 0,
      "2021-02-28T11:40:00-05:00": 0,
      "2021-02-28T11:45:00-05:00": 0,
      "2021-02-28T11:50:00-05:00": 1,
      "2021-02-28T11:55:00-05:00": 0,
      "2021-02-28T12:00:00-05:00": 0,
      "2021-02-28T12:05:00-05:00": 0,
      "2021-02-28T12:10:00-05:00": 0,
      "2021-02-28T12:15:00-05:00": 0,
      "2021-02-28T12:20:00-05:00": 0,
      "2021-02-28T12:25:00-05:00": 0,
      "2021-02-28T12:30:00-05:00": 0,
      "2021-02-28T12:35:00-05:00": 0,
      "2021-02-28T12:40:00-05:00": 0,
      "2021-02-28T12:45:00-05:00": 0,
      "2021-02-28T12:50:00-05:00": 1,
      "2021-02-28T12:55:00-05:00": 2,
      "2021-02-28T13:00:00-05:00": 0,
      "2021-02-28T13:05:00-05:00": 0,
      "2021-02-28T13:10:00-05:00": 0,
      "2021-02-28T13:15:00-05:00": 0,
      "2021-02-28T13:20:00-05:00": 1,
      "2021-02-28T13:25:00-05:00": 0,
      "2021-02-28T13:30:00-05:00": 0,
      "2021-02-28T13:35:00-05:00": 0,
      "2021-02-28T13:40:00-05:00": 0,
      "2021-02-28T13:45:00-05:00": 0,
      "2021-02-28T13:50:00-05:00": 0,
      "2021-02-28T13:55:00-05:00": 0,
      "2021-02-28T14:00:00-05:00": 0,
      "2021-02-28T14:05:00-05:00": 0,
      "2021-02-28T14:10:00-05:00": 0,
      "2021-02-28T14:15:00-05:00": 0,
      "2021-02-28T14:20:00-05:00": 0,
      "2021-02-28T14:25:00-05:00": 0,
      "2021-02-28T14:30:00-05:00": 0,
      "2021-02-28T14:35:00-05:00": 0,
      "2021-02-28T14:40:00-05:00": 0,
      "2021-02-28T14:45:00-05:00": 0,
      "2021-02-28T14:50:00-05:00": 1,
      "2021-02-28T14:55:00-05:00": 0,
      "2021-02-28T15:00:00-05:00": 0,
      "2021-02-28T15:05:00-05:00": 0,
      "2021-02-28T15:10:00-05:00": 0,
      "2021-02-28T15:15:00-05:00": 0,
      "2021-02-28T15:20:00-05:00": 0,
      "2021-02-28T15:25:00-05:00": 0,
      "2021-02-28T15:30:00-05:00": 0,
      "2021-02-28T15:35:00-05:00": 0,
      "2021-02-28T15:40:00-05:00": 0,
      "2021-02-28T15:45:00-05:00": 0,
      "2021-02-28T15:50:00-05:00": 1,
      "2021-02-28T15:55:00-05:00": 0,
      "2021-02-28T16:00:00-05:00": 1,
      "2021-02-28T16:05:00-05:00": 0,
      "2021-02-28T16:10:00-05:00": 0,
      "2021-02-28T16:15:00-05:00": 0,
      "2021-02-28T16:20:00-05:00": 0,
      "2021-02-28T16:25:00-05:00": 0,
      "2021-02-28T16:30:00-05:00": 0,
      "2021-02-28T16:35:00-05:00": 0,
      "2021-02-28T16:40:00-05:00": 0,
      "2021-02-28T16:45:00-05:00": 0,
      "2021-02-28T16:50:00-05:00": 0,
      "2021-02-28T16:55:00-05:00": 0,
      "2021-02-28T17:00:00-05:00": 0
    },
    "repos": {
      "conda-forge/admin-migrations": 22,
      "conda-forge/clblast-feedstock": 2,
      "conda-forge/dicttoxml-feedstock": 4,
      "conda-forge/jsonfield-feedstock": 2,
      "conda-forge/jsonlines-feedstock": 2,
      "conda-forge/junit-xml-feedstock": 2,
      "conda-forge/jupyter_console-feedstock": 6,
      "conda-forge/keepalive-feedstock": 2,
      "conda-forge/kwant-feedstock": 4,
      "conda-forge/kyotocabinet-feedstock": 8,
      "conda-forge/langdetect-feedstock": 4,
      "conda-forge/lastools-feedstock": 4,
      "conda-forge/lemon-feedstock": 6,
      "conda-forge/libflac-feedstock": 4,
      "conda-forge/libglu-feedstock": 4,
      "conda-forge/libmo_unpack-feedstock": 2,
      "conda-forge/libsigcpp-feedstock": 4,
      "conda-forge/libtar-feedstock": 4,
      "conda-forge/libtool-feedstock": 2,
      "conda-forge/lld-feedstock": 4,
      "conda-forge/lldb-feedstock": 3,
      "conda-forge/llvmdev-feedstock": 8,
      "conda-forge/mesalib-feedstock": 4,
      "conda-forge/miktex-feedstock": 1,
      "conda-forge/mms-python-client-feedstock": 12,
      "conda-forge/mock-feedstock": 21,
      "conda-forge/moment-feedstock": 2,
      "conda-forge/mongo-tools-feedstock": 4,
      "conda-forge/moviepy-feedstock": 2,
      "conda-forge/mysql-feedstock": 38,
      "conda-forge/ncurses-feedstock": 4,
      "conda-forge/nettle-feedstock": 2,
      "conda-forge/node2vec-feedstock": 2,
      "conda-forge/numpy-indexed-feedstock": 1,
      "conda-forge/ocaml-feedstock": 2,
      "conda-forge/ogh-feedstock": 4,
      "conda-forge/olefile-feedstock": 2,
      "conda-forge/openimageio-feedstock": 4,
      "conda-forge/openquake.engine-feedstock": 4,
      "conda-forge/optlang-feedstock": 2,
      "conda-forge/opty-feedstock": 6,
      "conda-forge/orcid-feedstock": 2,
      "conda-forge/pastedeploy-feedstock": 2,
      "conda-forge/pdfrw-feedstock": 1,
      "conda-forge/pixstem-feedstock": 3,
      "conda-forge/pkginfo-feedstock": 2,
      "conda-forge/poco-feedstock": 4,
      "conda-forge/preact-feedstock": 1,
      "conda-forge/progress-feedstock": 2,
      "conda-forge/prospector-feedstock": 2,
      "conda-forge/pthreads-win32-feedstock": 2,
      "conda-forge/pulsewaves-feedstock": 8,
      "conda-forge/pvl-feedstock": 2,
      "conda-forge/py3dmol-feedstock": 2,
      "conda-forge/py4j-feedstock": 2,
      "conda-forge/pybinding-feedstock": 2,
      "conda-forge/pybuilder-feedstock": 4,
      "conda-forge/pyct-feedstock": 2,
      "conda-forge/pydstool-feedstock": 2,
      "conda-forge/pygsp-feedstock": 2,
      "conda-forge/pyiron_atomistics-feedstock": 2,
      "conda-forge/pyiron_base-feedstock": 4,
      "conda-forge/pyld-feedstock": 2,
      "conda-forge/pylint-plugin-utils-feedstock": 4,
      "conda-forge/pymssql-feedstock": 12,
      "conda-forge/pyopcode-feedstock": 9,
      "conda-forge/pyorbital-feedstock": 2,
      "conda-forge/pyppeteer-feedstock": 6,
      "conda-forge/pytest-flakes-feedstock": 2,
      "conda-forge/pytest-sugar-feedstock": 2,
      "conda-forge/python-awips-feedstock": 2,
      "conda-forge/python-jose-feedstock": 2,
      "conda-forge/python-nvd3-feedstock": 2,
      "conda-forge/python-spams-feedstock": 24,
      "conda-forge/pytorch-cpu-feedstock": 46,
      "conda-forge/pyvisa-feedstock": 6,
      "conda-forge/pyvtk-feedstock": 2,
      "conda-forge/pywaffle-feedstock": 3,
      "conda-forge/pywebhdfs-feedstock": 6,
      "conda-forge/qpdf-feedstock": 8,
      "conda-forge/qtwebkit-feedstock": 2,
      "conda-forge/r-openmx-feedstock": 120,
      "conda-forge/redux-feedstock": 1,
      "conda-forge/reindent-feedstock": 2,
      "conda-forge/requests-oauthlib-feedstock": 2,
      "conda-forge/rfpimp-feedstock": 2,
      "conda-forge/roslibpy-feedstock": 2,
      "conda-forge/routes-feedstock": 2,
      "conda-forge/ruby-feedstock": 2,
      "conda-forge/s3transfer-feedstock": 6,
      "conda-forge/salib-feedstock": 1,
      "conda-forge/sarge-feedstock": 4,
      "conda-forge/scikit-bio-feedstock": 32,
      "conda-forge/scikit-learn-feedstock": 18,
      "conda-forge/sfepy-feedstock": 147,
      "conda-forge/simhash-feedstock": 6,
      "conda-forge/singular-feedstock": 2,
      "conda-forge/smartypants-feedstock": 4,
      "conda-forge/smmap-feedstock": 2,
      "conda-forge/smmap2-feedstock": 2,
      "conda-forge/snap-cpp-feedstock": 2,
      "conda-forge/speclite-feedstock": 12,
      "conda-forge/spefile-feedstock": 8,
      "conda-forge/sphinx-argparse-feedstock": 4,
      "conda-forge/spyder-reports-feedstock": 3,
      "conda-forge/sqlite-feedstock": 2,
      "conda-forge/sqlitedict-feedstock": 2,
      "conda-forge/srm-feedstock": 4,
      "conda-forge/staged-recipes": 95,
      "conda-forge/strec-feedstock": 5,
      "conda-forge/swi-prolog-feedstock": 2,
      "conda-forge/theanolm-feedstock": 4,
      "conda-forge/thermotools-feedstock": 12,
      "conda-forge/torchvision-feedstock": 6,
      "conda-forge/traittypes-feedstock": 4,
      "conda-forge/trilinos-feedstock": 54,
      "conda-forge/u3d-feedstock": 2,
      "conda-forge/ua-parser-feedstock": 1,
      "conda-forge/udunits2-feedstock": 4,
      "conda-forge/us-feedstock": 2,
      "conda-forge/visidata-feedstock": 2,
      "conda-forge/vmprof-feedstock": 6,
      "conda-forge/vsc-base-feedstock": 2,
      "conda-forge/watchtower-feedstock": 4,
      "conda-forge/xmltodict-feedstock": 2,
      "conda-forge/xorg-damageproto-feedstock": 4,
      "conda-forge/xorg-xf86vidmodeproto-feedstock": 4,
      "conda-forge/xz-feedstock": 8
    },
    "total": 10
  },
  "drone": {
    "rates": {
      "2021-02-28T09:05:00-05:00": 0,
      "2021-02-28T09:10:00-05:00": 0,
      "2021-02-28T09:15:00-05:00": 0,
      "2021-02-28T09:20:00-05:00": 0,
      "2021-02-28T09:25:00-05:00": 0,
      "2021-02-28T09:30:00-05:00": 0,
      "2021-02-28T09:35:00-05:00": 0,
      "2021-02-28T09:40:00-05:00": 0,
      "2021-02-28T09:45:00-05:00": 0,
      "2021-02-28T09:50:00-05:00": 0,
      "2021-02-28T09:55:00-05:00": 0,
      "2021-02-28T10:00:00-05:00": 0,
      "2021-02-28T10:05:00-05:00": 0,
      "2021-02-28T10:10:00-05:00": 0,
      "2021-02-28T10:15:00-05:00": 0,
      "2021-02-28T10:20:00-05:00": 0,
      "2021-02-28T10:25:00-05:00": 0,
      "2021-02-28T10:30:00-05:00": 0,
      "2021-02-28T10:35:00-05:00": 0,
      "2021-02-28T10:40:00-05:00": 0,
      "2021-02-28T10:45:00-05:00": 0,
      "2021-02-28T10:50:00-05:00": 0,
      "2021-02-28T10:55:00-05:00": 0,
      "2021-02-28T11:00:00-05:00": 0,
      "2021-02-28T11:05:00-05:00": 0,
      "2021-02-28T11:10:00-05:00": 0,
      "2021-02-28T11:15:00-05:00": 0,
      "2021-02-28T11:20:00-05:00": 0,
      "2021-02-28T11:25:00-05:00": 0,
      "2021-02-28T11:30:00-05:00": 0,
      "2021-02-28T11:35:00-05:00": 0,
      "2021-02-28T11:40:00-05:00": 0,
      "2021-02-28T11:45:00-05:00": 0,
      "2021-02-28T11:50:00-05:00": 0,
      "2021-02-28T11:55:00-05:00": 0,
      "2021-02-28T12:00:00-05:00": 0,
      "2021-02-28T12:05:00-05:00": 0,
      "2021-02-28T12:10:00-05:00": 0,
      "2021-02-28T12:15:00-05:00": 0,
      "2021-02-28T12:20:00-05:00": 0,
      "2021-02-28T12:25:00-05:00": 0,
      "2021-02-28T12:30:00-05:00": 0,
      "2021-02-28T12:35:00-05:00": 0,
      "2021-02-28T12:40:00-05:00": 0,
      "2021-02-28T12:45:00-05:00": 0,
      "2021-02-28T12:50:00-05:00": 0,
      "2021-02-28T12:55:00-05:00": 0,
      "2021-02-28T13:00:00-05:00": 0,
      "2021-02-28T13:05:00-05:00": 0,
      "2021-02-28T13:10:00-05:00": 2,
      "2021-02-28T13:15:00-05:00": 0,
      "2021-02-28T13:20:00-05:00": 0,
      "2021-02-28T13:25:00-05:00": 0,
      "2021-02-28T13:30:00-05:00": 0,
      "2021-02-28T13:35:00-05:00": 0,
      "2021-02-28T13:40:00-05:00": 0,
      "2021-02-28T13:45:00-05:00": 1,
      "2021-02-28T13:50:00-05:00": 0,
      "2021-02-28T13:55:00-05:00": 0,
      "2021-02-28T14:00:00-05:00": 0,
      "2021-02-28T14:05:00-05:00": 0,
      "2021-02-28T14:10:00-05:00": 0,
      "2021-02-28T14:15:00-05:00": 0,
      "2021-02-28T14:20:00-05:00": 0,
      "2021-02-28T14:25:00-05:00": 0,
      "2021-02-28T14:30:00-05:00": 0,
      "2021-02-28T14:35:00-05:00": 0,
      "2021-02-28T14:40:00-05:00": 0,
      "2021-02-28T14:45:00-05:00": 0,
      "2021-02-28T14:50:00-05:00": 0,
      "2021-02-28T14:55:00-05:00": 0,
      "2021-02-28T15:00:00-05:00": 0,
      "2021-02-28T15:05:00-05:00": 0,
      "2021-02-28T15:10:00-05:00": 0,
      "2021-02-28T15:15:00-05:00": 0,
      "2021-02-28T15:20:00-05:00": 0,
      "2021-02-28T15:25:00-05:00": 0,
      "2021-02-28T15:30:00-05:00": 0,
      "2021-02-28T15:35:00-05:00": 0,
      "2021-02-28T15:40:00-05:00": 0,
      "2021-02-28T15:45:00-05:00": 1,
      "2021-02-28T15:50:00-05:00": 0,
      "2021-02-28T15:55:00-05:00": 0,
      "2021-02-28T16:00:00-05:00": 0,
      "2021-02-28T16:05:00-05:00": 0,
      "2021-02-28T16:10:00-05:00": 0,
      "2021-02-28T16:15:00-05:00": 0,
      "2021-02-28T16:20:00-05:00": 0,
      "2021-02-28T16:25:00-05:00": 0,
      "2021-02-28T16:30:00-05:00": 0,
      "2021-02-28T16:35:00-05:00": 0,
      "2021-02-28T16:40:00-05:00": 0,
      "2021-02-28T16:45:00-05:00": 0,
      "2021-02-28T16:50:00-05:00": 0,
      "2021-02-28T16:55:00-05:00": 0,
      "2021-02-28T17:00:00-05:00": 0
    },
    "repos": {
      "conda-forge/bitarray-feedstock": 3,
      "conda-forge/broot-feedstock": 1,
      "conda-forge/dftbplus-feedstock": 1,
      "conda-forge/igraph-feedstock": 5,
      "conda-forge/imagecodecs-feedstock": 1,
      "conda-forge/inflect-feedstock": 3,
      "conda-forge/ipython-feedstock": 4,
      "conda-forge/keyring-feedstock": 4,
      "conda-forge/libignition-transport4-feedstock": 2,
      "conda-forge/libsemigroups-feedstock": 2,
      "conda-forge/libxkbcommon-feedstock": 1,
      "conda-forge/nbgrader-feedstock": 1,
      "conda-forge/nodejs-feedstock": 7,
      "conda-forge/openmpi-feedstock": 3,
      "conda-forge/orjson-feedstock": 2,
      "conda-forge/pre-commit-feedstock": 1,
      "conda-forge/protobuf-feedstock": 8,
      "conda-forge/pydantic-feedstock": 3,
      "conda-forge/pylint-feedstock": 1,
      "conda-forge/pytalises-feedstock": 4,
      "conda-forge/r-farver-feedstock": 1,
      "conda-forge/r-glmnet-feedstock": 2,
      "conda-forge/r-hmisc-feedstock": 2,
      "conda-forge/r-lubridate-feedstock": 4,
      "conda-forge/r-pbdzmq-feedstock": 2,
      "conda-forge/r-pkgload-feedstock": 2,
      "conda-forge/r-tibble-feedstock": 5,
      "conda-forge/re2-feedstock": 1,
      "conda-forge/rich-feedstock": 8,
      "conda-forge/rust-activation-feedstock": 7,
      "conda-forge/rust-feedstock": 2,
      "conda-forge/s2n-feedstock": 2,
      "conda-forge/simple-dftd3-feedstock": 2,
      "conda-forge/slepc-feedstock": 1,
      "conda-forge/sniffio-feedstock": 1,
      "conda-forge/sourmash-minimal-feedstock": 8,
      "conda-forge/spacy-feedstock": 22,
      "conda-forge/spyder-kernels-feedstock": 4,
      "conda-forge/squashfs-tools-feedstock": 15,
      "conda-forge/srm-ifce-feedstock": 5,
      "conda-forge/srsly-feedstock": 15,
      "conda-forge/statsmodels-feedstock": 7,
      "conda-forge/suitesparse-feedstock": 2,
      "conda-forge/sundials-feedstock": 2,
      "conda-forge/tar-feedstock": 2,
      "conda-forge/tbb-feedstock": 27,
      "conda-forge/thinc-feedstock": 25,
      "conda-forge/thrift-cpp-feedstock": 3,
      "conda-forge/tiledb-feedstock": 1,
      "conda-forge/tinyxml-feedstock": 13,
      "conda-forge/tinyxml2-feedstock": 3,
      "conda-forge/tokenizers-feedstock": 1,
      "conda-forge/tomopy-feedstock": 4,
      "conda-forge/tox-feedstock": 12,
      "conda-forge/traits-feedstock": 2,
      "conda-forge/treelite-feedstock": 4,
      "conda-forge/trio-feedstock": 3,
      "conda-forge/ujson-feedstock": 4,
      "conda-forge/unzip-feedstock": 2,
      "conda-forge/uproot-feedstock": 9,
      "conda-forge/urdfdom-feedstock": 9,
      "conda-forge/urdfdom_headers-feedstock": 4,
      "conda-forge/urwid-feedstock": 14,
      "conda-forge/utfcpp-feedstock": 2,
      "conda-forge/util-linux-feedstock": 16,
      "conda-forge/uvicorn-feedstock": 16,
      "conda-forge/uvloop-feedstock": 26,
      "conda-forge/vdt-feedstock": 2,
      "conda-forge/viztracer-feedstock": 11,
      "conda-forge/vowpalwabbit-feedstock": 15,
      "conda-forge/vtk-feedstock": 3,
      "conda-forge/warpx-feedstock": 45,
      "conda-forge/web3-feedstock": 22,
      "conda-forge/websocket-client-feedstock": 12,
      "conda-forge/websockets-feedstock": 8,
      "conda-forge/westpa-feedstock": 3,
      "conda-forge/wget-feedstock": 1,
      "conda-forge/widgetsnbextension-feedstock": 13,
      "conda-forge/wrapt-feedstock": 21,
      "conda-forge/wurlitzer-feedstock": 10,
      "conda-forge/wxpython-feedstock": 1,
      "conda-forge/xenv-feedstock": 8,
      "conda-forge/xerces-c-feedstock": 10,
      "conda-forge/xeus-cling-feedstock": 19,
      "conda-forge/xeus-feedstock": 62,
      "conda-forge/xeus-python-feedstock": 91,
      "conda-forge/xeus-robot-feedstock": 70,
      "conda-forge/xeus-sqlite-feedstock": 13,
      "conda-forge/xleaflet-feedstock": 5,
      "conda-forge/xorg-compositeproto-feedstock": 3,
      "conda-forge/xorg-damageproto-feedstock": 5,
      "conda-forge/xorg-libxaw-feedstock": 3,
      "conda-forge/xorg-libxcomposite-feedstock": 3,
      "conda-forge/xorg-libxdamage-feedstock": 2,
      "conda-forge/xorg-libxinerama-feedstock": 9,
      "conda-forge/xorg-libxt-feedstock": 2,
      "conda-forge/xorg-xf86vidmodeproto-feedstock": 4,
      "conda-forge/xorg-xineramaproto-feedstock": 3,
      "conda-forge/xorg-xproto-feedstock": 3,
      "conda-forge/xproperty-feedstock": 7,
      "conda-forge/xrootd-feedstock": 53,
      "conda-forge/xtb-feedstock": 25,
      "conda-forge/xtb-python-feedstock": 1,
      "conda-forge/xtensor-blas-feedstock": 9,
      "conda-forge/xtensor-feedstock": 13,
      "conda-forge/xtensor-fftw-feedstock": 3,
      "conda-forge/xtensor-io-feedstock": 24,
      "conda-forge/xtl-feedstock": 44,
      "conda-forge/xvega-bindings-feedstock": 14,
      "conda-forge/xvega-feedstock": 20,
      "conda-forge/xwebrtc-feedstock": 4,
      "conda-forge/xwidgets-feedstock": 6,
      "conda-forge/xxhash-feedstock": 20,
      "conda-forge/yaml-cpp-feedstock": 10,
      "conda-forge/yarl-feedstock": 7,
      "conda-forge/yarn-feedstock": 2,
      "conda-forge/yt-feedstock": 14,
      "conda-forge/ytop-feedstock": 10,
      "conda-forge/zaber-motion-feedstock": 71,
      "conda-forge/zbar-py-feedstock": 4,
      "conda-forge/zfp-feedstock": 8,
      "conda-forge/zfpy-feedstock": 62,
      "conda-forge/zlib-feedstock": 41,
      "conda-forge/zn_poly-feedstock": 11,
      "conda-forge/zopfli-feedstock": 8,
      "conda-forge/zstandard-feedstock": 21,
      "conda-forge/zstd-feedstock": 6,
      "conda-forge/zziplib-feedstock": 2
    },
    "total": 4
  },
  "github-actions": {
    "rates": {
      "2021-02-28T09:05:00-05:00": 4,
      "2021-02-28T09:10:00-05:00": 0,
      "2021-02-28T09:15:00-05:00": 0,
      "2021-02-28T09:20:00-05:00": 2,
      "2021-02-28T09:25:00-05:00": 1,
      "2021-02-28T09:30:00-05:00": 2,
      "2021-02-28T09:35:00-05:00": 3,
      "2021-02-28T09:40:00-05:00": 2,
      "2021-02-28T09:45:00-05:00": 3,
      "2021-02-28T09:50:00-05:00": 7,
      "2021-02-28T09:55:00-05:00": 9,
      "2021-02-28T10:00:00-05:00": 12,
      "2021-02-28T10:05:00-05:00": 3,
      "2021-02-28T10:10:00-05:00": 4,
      "2021-02-28T10:15:00-05:00": 2,
      "2021-02-28T10:20:00-05:00": 1,
      "2021-02-28T10:25:00-05:00": 5,
      "2021-02-28T10:30:00-05:00": 1,
      "2021-02-28T10:35:00-05:00": 1,
      "2021-02-28T10:40:00-05:00": 3,
      "2021-02-28T10:45:00-05:00": 2,
      "2021-02-28T10:50:00-05:00": 3,
      "2021-02-28T10:55:00-05:00": 3,
      "2021-02-28T11:00:00-05:00": 7,
      "2021-02-28T11:05:00-05:00": 0,
      "2021-02-28T11:10:00-05:00": 1,
      "2021-02-28T11:15:00-05:00": 2,
      "2021-02-28T11:20:00-05:00": 3,
      "2021-02-28T11:25:00-05:00": 8,
      "2021-02-28T11:30:00-05:00": 7,
      "2021-02-28T11:35:00-05:00": 1,
      "2021-02-28T11:40:00-05:00": 4,
      "2021-02-28T11:45:00-05:00": 2,
      "2021-02-28T11:50:00-05:00": 1,
      "2021-02-28T11:55:00-05:00": 3,
      "2021-02-28T12:00:00-05:00": 3,
      "2021-02-28T12:05:00-05:00": 4,
      "2021-02-28T12:10:00-05:00": 5,
      "2021-02-28T12:15:00-05:00": 1,
      "2021-02-28T12:20:00-05:00": 5,
      "2021-02-28T12:25:00-05:00": 3,
      "2021-02-28T12:30:00-05:00": 0,
      "2021-02-28T12:35:00-05:00": 1,
      "2021-02-28T12:40:00-05:00": 2,
      "2021-02-28T12:45:00-05:00": 5,
      "2021-02-28T12:50:00-05:00": 4,
      "2021-02-28T12:55:00-05:00": 24,
      "2021-02-28T13:00:00-05:00": 9,
      "2021-02-28T13:05:00-05:00": 4,
      "2021-02-28T13:10:00-05:00": 8,
      "2021-02-28T13:15:00-05:00": 1,
      "2021-02-28T13:20:00-05:00": 4,
      "2021-02-28T13:25:00-05:00": 1,
      "2021-02-28T13:30:00-05:00": 4,
      "2021-02-28T13:35:00-05:00": 2,
      "2021-02-28T13:40:00-05:00": 5,
      "2021-02-28T13:45:00-05:00": 2,
      "2021-02-28T13:50:00-05:00": 1,
      "2021-02-28T13:55:00-05:00": 3,
      "2021-02-28T14:00:00-05:00": 9,
      "2021-02-28T14:05:00-05:00": 2,
      "2021-02-28T14:10:00-05:00": 4,
      "2021-02-28T14:15:00-05:00": 3,
      "2021-02-28T14:20:00-05:00": 1,
      "2021-02-28T14:25:00-05:00": 4,
      "2021-02-28T14:30:00-05:00": 3,
      "2021-02-28T14:35:00-05:00": 4,
      "2021-02-28T14:40:00-05:00": 3,
      "2021-02-28T14:45:00-05:00": 4,
      "2021-02-28T14:50:00-05:00": 1,
      "2021-02-28T14:55:00-05:00": 2,
      "2021-02-28T15:00:00-05:00": 3,
      "2021-02-28T15:05:00-05:00": 3,
      "2021-02-28T15:10:00-05:00": 0,
      "2021-02-28T15:15:00-05:00": 2,
      "2021-02-28T15:20:00-05:00": 1,
      "2021-02-28T15:25:00-05:00": 4,
      "2021-02-28T15:30:00-05:00": 14,
      "2021-02-28T15:35:00-05:00": 11,
      "2021-02-28T15:40:00-05:00": 12,
      "2021-02-28T15:45:00-05:00": 4,
      "2021-02-28T15:50:00-05:00": 3,
      "2021-02-28T15:55:00-05:00": 1,
      "2021-02-28T16:00:00-05:00": 6,
      "2021-02-28T16:05:00-05:00": 2,
      "2021-02-28T16:10:00-05:00": 1,
      "2021-02-28T16:15:00-05:00": 1,
      "2021-02-28T16:20:00-05:00": 5,
      "2021-02-28T16:25:00-05:00": 3,
      "2021-02-28T16:30:00-05:00": 3,
      "2021-02-28T16:35:00-05:00": 10,
      "2021-02-28T16:40:00-05:00": 7,
      "2021-02-28T16:45:00-05:00": 10,
      "2021-02-28T16:50:00-05:00": 4,
      "2021-02-28T16:55:00-05:00": 2,
      "2021-02-28T17:00:00-05:00": 0
    },
    "repos": {
      "conda-forge/admin-requests": 1,
      "conda-forge/ambiance-feedstock": 1,
      "conda-forge/artifact-validation": 66,
      "conda-forge/bitarray-feedstock": 17,
      "conda-forge/broot-feedstock": 9,
      "conda-forge/cadquery-feedstock": 2,
      "conda-forge/clang-compiler-activation-feedstock": 6,
      "conda-forge/clblast-feedstock": 11,
      "conda-forge/conda-forge-repodata-patches-feedstock": 1,
      "conda-forge/conda-forge-webservices": 11,
      "conda-forge/dftbplus-feedstock": 6,
      "conda-forge/dlfcn-win32-feedstock": 2,
      "conda-forge/dlpoly-py-feedstock": 3,
      "conda-forge/dmba-feedstock": 1,
      "conda-forge/faiss-split-feedstock": 4,
      "conda-forge/find-kedro-feedstock": 2,
      "conda-forge/freecad-feedstock": 3,
      "conda-forge/frictionqpotfem-feedstock": 4,
      "conda-forge/gammapy-feedstock": 1,
      "conda-forge/gazebo-feedstock": 4,
      "conda-forge/gitpython-feedstock": 2,
      "conda-forge/google-api-core-feedstock": 2,
      "conda-forge/googleapis-common-protos-feedstock": 5,
      "conda-forge/goosefem-feedstock": 5,
      "conda-forge/httpx-feedstock": 2,
      "conda-forge/imagemagick-feedstock": 2,
      "conda-forge/isa-l-feedstock": 3,
      "conda-forge/jupyter_conda-feedstock": 2,
      "conda-forge/kim_property-feedstock": 3,
      "conda-forge/libmatio-feedstock": 6,
      "conda-forge/libsemigroups-feedstock": 11,
      "conda-forge/ligo.skymap-feedstock": 2,
      "conda-forge/llvmdev-feedstock": 1,
      "conda-forge/lyx-feedstock": 12,
      "conda-forge/mdanalysis-feedstock": 5,
      "conda-forge/mdanalysistests-feedstock": 11,
      "conda-forge/metaio-feedstock": 2,
      "conda-forge/mkdocstrings-feedstock": 2,
      "conda-forge/nbsphinx-feedstock": 2,
      "conda-forge/p4p-feedstock": 2,
      "conda-forge/pangeo-dask-feedstock": 6,
      "conda-forge/pangeo-notebook-feedstock": 6,
      "conda-forge/pdal-feedstock": 1,
      "conda-forge/pdfplumber-feedstock": 2,
      "conda-forge/pngquant-feedstock": 2,
      "conda-forge/portion-feedstock": 3,
      "conda-forge/postgis-feedstock": 4,
      "conda-forge/pyathena-feedstock": 2,
      "conda-forge/pyglotaran-feedstock": 5,
      "conda-forge/pymeeus-feedstock": 2,
      "conda-forge/pynamodb-feedstock": 2,
      "conda-forge/pynio-feedstock": 1,
      "conda-forge/pyqt-feedstock": 9,
      "conda-forge/python3-saml-feedstock": 1,
      "conda-forge/pytkdocs-feedstock": 3,
      "conda-forge/qwt-feedstock": 5,
      "conda-forge/r-farver-feedstock": 7,
      "conda-forge/r-hmisc-feedstock": 8,
      "conda-forge/r-tibble-feedstock": 18,
      "conda-forge/r-tune-feedstock": 5,
      "conda-forge/r-xtensor-feedstock": 1,
      "conda-forge/readchar-feedstock": 4,
      "conda-forge/repodata-shards": 201,
      "conda-forge/root-feedstock": 3,
      "conda-forge/runner-feedstock": 5,
      "conda-forge/rust-feedstock": 5,
      "conda-forge/s2geometry-feedstock": 3,
      "conda-forge/sagemaker-python-sdk-feedstock": 2,
      "conda-forge/scikit-mobility-feedstock": 2,
      "conda-forge/shogun-cpp-feedstock": 1,
      "conda-forge/singledispatch-feedstock": 1,
      "conda-forge/singularity-compose-feedstock": 4,
      "conda-forge/sip-feedstock": 5,
      "conda-forge/sklearn-pandas-feedstock": 11,
      "conda-forge/soci-feedstock": 4,
      "conda-forge/spacy-model-en_core_web-feedstock": 3,
      "conda-forge/spampy-feedstock": 1,
      "conda-forge/sphinx-book-theme-feedstock": 4,
      "conda-forge/sphinx-multitoc-numbering-feedstock": 1,
      "conda-forge/sphinx-notfound-page-feedstock": 3,
      "conda-forge/sphinxcontrib-details-directive-feedstock": 1,
      "conda-forge/sphinxcontrib-restbuilder-feedstock": 2,
      "conda-forge/spotipy-feedstock": 13,
      "conda-forge/srtm.py-feedstock": 2,
      "conda-forge/staged-recipes": 223,
      "conda-forge/stress-ng-feedstock": 1,
      "conda-forge/structdbrest-feedstock": 7,
      "conda-forge/sunpy-feedstock": 3,
      "conda-forge/supervisor-feedstock": 2,
      "conda-forge/sweetviz-feedstock": 2,
      "conda-forge/tempest-remap-feedstock": 4,
      "conda-forge/thorlabs-apt-protocol-feedstock": 3,
      "conda-forge/tifffile-feedstock": 3,
      "conda-forge/tike-feedstock": 2,
      "conda-forge/tilt-feedstock": 3,
      "conda-forge/topologytoolkit-feedstock": 3,
      "conda-forge/torchsde-feedstock": 10,
      "conda-forge/tributary-feedstock": 7,
      "conda-forge/trimesh-feedstock": 1,
      "conda-forge/ttyd-feedstock": 3,
      "conda-forge/twisted-feedstock": 2,
      "conda-forge/typhos-feedstock": 3,
      "conda-forge/umarkdown-feedstock": 1,
      "conda-forge/universal-ctags-feedstock": 2,
      "conda-forge/verta-feedstock": 9,
      "conda-forge/vim-feedstock": 10,
      "conda-forge/vscode-icons-feedstock": 8,
      "conda-forge/vyper-feedstock": 3,
      "conda-forge/wquantiles-feedstock": 1,
      "conda-forge/xeus-cling-feedstock": 18,
      "conda-forge/xeus-feedstock": 11,
      "conda-forge/xgboost-feedstock": 2,
      "conda-forge/xmlsec-feedstock": 10,
      "conda-forge/xproperty-feedstock": 11,
      "conda-forge/xsimd-feedstock": 3,
      "conda-forge/xtb-python-feedstock": 3,
      "conda-forge/xtensor-blas-feedstock": 11,
      "conda-forge/xtensor-feedstock": 11,
      "conda-forge/xtensor-io-feedstock": 34,
      "conda-forge/xtensor-julia-feedstock": 3,
      "conda-forge/xtensor-python-feedstock": 5,
      "conda-forge/xtensor-r-feedstock": 10,
      "conda-forge/xtl-feedstock": 11,
      "conda-forge/yaqd-thorlabs-feedstock": 2,
      "conda-forge/yaqd-vici-feedstock": 1,
      "conda-forge/yaspin-feedstock": 2,
      "conda-forge/zmqpp-feedstock": 3,
      "conda-forge/zstandard-feedstock": 6
    },
    "total": 365
  },
  "travis-ci": {
    "rates": {
      "2021-02-28T09:05:00-05:00": 1,
      "2021-02-28T09:10:00-05:00": 0,
      "2021-02-28T09:15:00-05:00": 0,
      "2021-02-28T09:20:00-05:00": 0,
      "2021-02-28T09:25:00-05:00": 0,
      "2021-02-28T09:30:00-05:00": 0,
      "2021-02-28T09:35:00-05:00": 0,
      "2021-02-28T09:40:00-05:00": 0,
      "2021-02-28T09:45:00-05:00": 0,
      "2021-02-28T09:50:00-05:00": 0,
      "2021-02-28T09:55:00-05:00": 0,
      "2021-02-28T10:00:00-05:00": 0,
      "2021-02-28T10:05:00-05:00": 0,
      "2021-02-28T10:10:00-05:00": 0,
      "2021-02-28T10:15:00-05:00": 0,
      "2021-02-28T10:20:00-05:00": 0,
      "2021-02-28T10:25:00-05:00": 0,
      "2021-02-28T10:30:00-05:00": 0,
      "2021-02-28T10:35:00-05:00": 0,
      "2021-02-28T10:40:00-05:00": 0,
      "2021-02-28T10:45:00-05:00": 0,
      "2021-02-28T10:50:00-05:00": 0,
      "2021-02-28T10:55:00-05:00": 0,
      "2021-02-28T11:00:00-05:00": 0,
      "2021-02-28T11:05:00-05:00": 0,
      "2021-02-28T11:10:00-05:00": 0,
      "2021-02-28T11:15:00-05:00": 0,
      "2021-02-28T11:20:00-05:00": 0,
      "2021-02-28T11:25:00-05:00": 0,
      "2021-02-28T11:30:00-05:00": 0,
      "2021-02-28T11:35:00-05:00": 0,
      "2021-02-28T11:40:00-05:00": 0,
      "2021-02-28T11:45:00-05:00": 0,
      "2021-02-28T11:50:00-05:00": 0,
      "2021-02-28T11:55:00-05:00": 0,
      "2021-02-28T12:00:00-05:00": 0,
      "2021-02-28T12:05:00-05:00": 0,
      "2021-02-28T12:10:00-05:00": 0,
      "2021-02-28T12:15:00-05:00": 0,
      "2021-02-28T12:20:00-05:00": 0,
      "2021-02-28T12:25:00-05:00": 0,
      "2021-02-28T12:30:00-05:00": 0,
      "2021-02-28T12:35:00-05:00": 0,
      "2021-02-28T12:40:00-05:00": 0,
      "2021-02-28T12:45:00-05:00": 0,
      "2021-02-28T12:50:00-05:00": 1,
      "2021-02-28T12:55:00-05:00": 1,
      "2021-02-28T13:00:00-05:00": 2,
      "2021-02-28T13:05:00-05:00": 0,
      "2021-02-28T13:10:00-05:00": 0,
      "2021-02-28T13:15:00-05:00": 0,
      "2021-02-28T13:20:00-05:00": 1,
      "2021-02-28T13:25:00-05:00": 0,
      "2021-02-28T13:30:00-05:00": 0,
      "2021-02-28T13:35:00-05:00": 0,
      "2021-02-28T13:40:00-05:00": 0,
      "2021-02-28T13:45:00-05:00": 0,
      "2021-02-28T13:50:00-05:00": 0,
      "2021-02-28T13:55:00-05:00": 0,
      "2021-02-28T14:00:00-05:00": 0,
      "2021-02-28T14:05:00-05:00": 0,
      "2021-02-28T14:10:00-05:00": 0,
      "2021-02-28T14:15:00-05:00": 0,
      "2021-02-28T14:20:00-05:00": 0,
      "2021-02-28T14:25:00-05:00": 0,
      "2021-02-28T14:30:00-05:00": 0,
      "2021-02-28T14:35:00-05:00": 0,
      "2021-02-28T14:40:00-05:00": 0,
      "2021-02-28T14:45:00-05:00": 0,
      "2021-02-28T14:50:00-05:00": 0,
      "2021-02-28T14:55:00-05:00": 0,
      "2021-02-28T15:00:00-05:00": 0,
      "2021-02-28T15:05:00-05:00": 0,
      "2021-02-28T15:10:00-05:00": 0,
      "2021-02-28T15:15:00-05:00": 0,
      "2021-02-28T15:20:00-05:00": 0,
      "2021-02-28T15:25:00-05:00": 0,
      "2021-02-28T15:30:00-05:00": 0,
      "2021-02-28T15:35:00-05:00": 0,
      "2021-02-28T15:40:00-05:00": 0,
      "2021-02-28T15:45:00-05:00": 0,
      "2021-02-28T15:50:00-05:00": 0,
      "2021-02-28T15:55:00-05:00": 0,
      "2021-02-28T16:00:00-05:00": 0,
      "2021-02-28T16:05:00-05:00": 0,
      "2021-02-28T16:10:00-05:00": 0,
      "2021-02-28T16:15:00-05:00": 0,
      "2021-02-28T16:20:00-05:00": 0,
      "2021-02-28T16:25:00-05:00": 0,
      "2021-02-28T16:30:00-05:00": 0,
      "2021-02-28T16:35:00-05:00": 0,
      "2021-02-28T16:40:00-05:00": 0,
      "2021-02-28T16:45:00-05:00": 0,
      "2021-02-28T16:50:00-05:00": 0,
      "2021-02-28T16:55:00-05:00": 0,
      "2021-02-28T17:00:00-05:00": 0
    },
    "repos": {
      "conda-forge/bitarray-feedstock": 3,
      "conda-forge/broot-feedstock": 2,
      "conda-forge/clblast-feedstock": 1,
      "conda-forge/dftbplus-feedstock": 1,
      "conda-forge/gap-feedstock": 1,
      "conda-forge/grpcio-feedstock": 3,
      "conda-forge/imagecodecs-feedstock": 1,
      "conda-forge/inflect-feedstock": 5,
      "conda-forge/ipython-feedstock": 3,
      "conda-forge/keyring-feedstock": 5,
      "conda-forge/libignition-transport4-feedstock": 4,
      "conda-forge/libsemigroups-feedstock": 2,
      "conda-forge/libxkbcommon-feedstock": 2,
      "conda-forge/mpb-feedstock": 7,
      "conda-forge/nbgrader-feedstock": 1,
      "conda-forge/nodejs-feedstock": 15,
      "conda-forge/openmpi-feedstock": 3,
      "conda-forge/orjson-feedstock": 2,
      "conda-forge/pre-commit-feedstock": 2,
      "conda-forge/protobuf-feedstock": 7,
      "conda-forge/pydantic-feedstock": 6,
      "conda-forge/pylint-feedstock": 1,
      "conda-forge/pytalises-feedstock": 4,
      "conda-forge/re2-feedstock": 1,
      "conda-forge/rich-feedstock": 10,
      "conda-forge/rust-feedstock": 1,
      "conda-forge/s2n-feedstock": 2,
      "conda-forge/setproctitle-feedstock": 2,
      "conda-forge/setuptools-feedstock": 2,
      "conda-forge/shap-feedstock": 2,
      "conda-forge/simple-dftd3-feedstock": 2,
      "conda-forge/slepc-feedstock": 1,
      "conda-forge/sourmash-minimal-feedstock": 8,
      "conda-forge/spacy-feedstock": 26,
      "conda-forge/spyder-kernels-feedstock": 4,
      "conda-forge/squashfs-tools-feedstock": 17,
      "conda-forge/srm-ifce-feedstock": 13,
      "conda-forge/srsly-feedstock": 32,
      "conda-forge/sundials-feedstock": 2,
      "conda-forge/tar-feedstock": 2,
      "conda-forge/tbb-feedstock": 27,
      "conda-forge/texlive-core-feedstock": 8,
      "conda-forge/thinc-feedstock": 27,
      "conda-forge/thrift-cpp-feedstock": 3,
      "conda-forge/tiledb-feedstock": 1,
      "conda-forge/tinyxml-feedstock": 26,
      "conda-forge/tinyxml2-feedstock": 9,
      "conda-forge/tokenizers-feedstock": 1,
      "conda-forge/tomopy-feedstock": 4,
      "conda-forge/tox-feedstock": 12,
      "conda-forge/traits-feedstock": 2,
      "conda-forge/treelite-feedstock": 6,
      "conda-forge/trio-feedstock": 3,
      "conda-forge/ujson-feedstock": 4,
      "conda-forge/umap-learn-feedstock": 2,
      "conda-forge/unzip-feedstock": 2,
      "conda-forge/uproot-feedstock": 19,
      "conda-forge/urwid-feedstock": 5,
      "conda-forge/utfcpp-feedstock": 2,
      "conda-forge/util-linux-feedstock": 33,
      "conda-forge/uvicorn-feedstock": 32,
      "conda-forge/uvloop-feedstock": 29,
      "conda-forge/vdt-feedstock": 4,
      "conda-forge/viztracer-feedstock": 14,
      "conda-forge/vmprof-feedstock": 1,
      "conda-forge/voms-feedstock": 1,
      "conda-forge/vowpalwabbit-feedstock": 16,
      "conda-forge/vsc-base-feedstock": 1,
      "conda-forge/vtk-feedstock": 3,
      "conda-forge/warpx-feedstock": 6,
      "conda-forge/web3-feedstock": 22,
      "conda-forge/webservices-dispatch-action": 27,
      "conda-forge/websocket-client-feedstock": 12,
      "conda-forge/websockets-feedstock": 8,
      "conda-forge/westpa-feedstock": 3,
      "conda-forge/wget-feedstock": 2,
      "conda-forge/widgetsnbextension-feedstock": 13,
      "conda-forge/wrapt-feedstock": 22,
      "conda-forge/wurlitzer-feedstock": 10,
      "conda-forge/wxpython-feedstock": 1,
      "conda-forge/xenv-feedstock": 17,
      "conda-forge/xerces-c-feedstock": 9,
      "conda-forge/xeus-cling-feedstock": 2,
      "conda-forge/xeus-feedstock": 69,
      "conda-forge/xeus-python-feedstock": 184,
      "conda-forge/xeus-robot-feedstock": 70,
      "conda-forge/xeus-sqlite-feedstock": 13,
      "conda-forge/xleaflet-feedstock": 10,
      "conda-forge/xorg-compositeproto-feedstock": 3,
      "conda-forge/xorg-damageproto-feedstock": 6,
      "conda-forge/xorg-libxaw-feedstock": 3,
      "conda-forge/xorg-libxcomposite-feedstock": 3,
      "conda-forge/xorg-libxdamage-feedstock": 2,
      "conda-forge/xorg-libxinerama-feedstock": 16,
      "conda-forge/xorg-libxt-feedstock": 2,
      "conda-forge/xorg-xf86vidmodeproto-feedstock": 5,
      "conda-forge/xorg-xineramaproto-feedstock": 3,
      "conda-forge/xorg-xproto-feedstock": 3,
      "conda-forge/xproperty-feedstock": 7,
      "conda-forge/xrootd-feedstock": 127,
      "conda-forge/xtb-feedstock": 28,
      "conda-forge/xtb-python-feedstock": 1,
      "conda-forge/xtensor-blas-feedstock": 9,
      "conda-forge/xtensor-feedstock": 13,
      "conda-forge/xtensor-fftw-feedstock": 3,
      "conda-forge/xtensor-io-feedstock": 46,
      "conda-forge/xtl-feedstock": 46,
      "conda-forge/xvega-bindings-feedstock": 14,
      "conda-forge/xvega-feedstock": 20,
      "conda-forge/xwebrtc-feedstock": 8,
      "conda-forge/xwidgets-feedstock": 15,
      "conda-forge/xxhash-feedstock": 2,
      "conda-forge/xz-feedstock": 4,
      "conda-forge/yaml-cpp-feedstock": 20,
      "conda-forge/yarl-feedstock": 5,
      "conda-forge/yarn-feedstock": 2,
      "conda-forge/yt-feedstock": 15,
      "conda-forge/ytop-feedstock": 10,
      "conda-forge/zaber-motion-feedstock": 73,
      "conda-forge/zbar-py-feedstock": 4,
      "conda-forge/zfp-feedstock": 8,
      "conda-forge/zfpy-feedstock": 123,
      "conda-forge/zlib-feedstock": 41,
      "conda-forge/zn_poly-feedstock": 11,
      "conda-forge/zopfli-feedstock": 8,
      "conda-forge/zstandard-feedstock": 22,
      "conda-forge/zstd-feedstock": 6,
      "conda-forge/zziplib-feedstock": 4
    },
    "total": 6
  }
}